consolet/__init__.py
consolet/colors.py
consolet/command.py
consolet/console.py
consolet/errors.py
consolet/terminal.py
consolet/utils.py
consolet-0.0.1.dist-info/LICENSE
consolet-0.0.1.dist-info/METADATA
consolet-0.0.1.dist-info/WHEEL
consolet-0.0.1.dist-info/top_level.txt
consolet-0.0.1.dist-info/RECORD
