Metadata-Version: 2.1
Name: consolet
Version: 0.0.1
Summary: Create your console applications easy and powerful.
Home-page: https://github.com/mr-nazari/Consolet
Author: Ali Nazari
Author-email: alinazarigh110@gamil.com
License: UNKNOWN
Project-URL: Bug Tracker, https://github.com/mr-nazari/Consolet/issues
Platform: UNKNOWN
Classifier: Programming Language :: Python :: 3
Classifier: License :: OSI Approved :: MIT License
Classifier: Operating System :: OS Independent
Requires-Python: >=3.6
License-File: LICENSE
